flowengine/__init__.py
flowengine/config/__init__.py
flowengine/config/loader.py
flowengine/config/registry.py
flowengine/config/schema.py
flowengine/contrib/__init__.py
flowengine/contrib/http.py
flowengine/contrib/logging.py
flowengine/core/__init__.py
flowengine/core/component.py
flowengine/core/context.py
flowengine/core/engine.py
flowengine/errors/__init__.py
flowengine/errors/exceptions.py
flowengine/eval/__init__.py
flowengine/eval/evaluator.py
flowengine/eval/safe_ast.py
flowengine/py.typed
flowengine-0.1.2.dist-info/METADATA
flowengine-0.1.2.dist-info/WHEEL
flowengine-0.1.2.dist-info/licenses/LICENSE
flowengine-0.1.2.dist-info/RECORD
