Metadata-Version: 2.4
Name: flowengine
Version: 0.1.2
Summary: Lightweight YAML-driven workflow engine for Python
License-Expression: MIT
License-File: LICENSE
Keywords: workflow,state-machine,pipeline,yaml,orchestration,automation,component,flow
Author: FlowEngine Contributors
Requires-Python: >=3.11
Classifier: Development Status :: 4 - Beta
Classifier: Intended Audience :: Developers
Classifier: License :: OSI Approved :: MIT License
Classifier: Operating System :: OS Independent
Classifier: Programming Language :: Python :: 3
Classifier: Programming Language :: Python :: 3.11
Classifier: Programming Language :: Python :: 3.12
Classifier: Programming Language :: Python :: 3.13
Classifier: Topic :: Software Development :: Libraries :: Python Modules
Classifier: Typing :: Typed
Provides-Extra: dev
Provides-Extra: docs
Provides-Extra: http
Requires-Dist: build (>=1.0) ; extra == "dev"
Requires-Dist: httpx (>=0.27) ; extra == "dev"
Requires-Dist: httpx (>=0.27) ; extra == "http"
Requires-Dist: mkdocs (>=1.5) ; extra == "docs"
Requires-Dist: mkdocs-material (>=9.0) ; extra == "docs"
Requires-Dist: mkdocstrings[python] (>=0.24) ; extra == "docs"
Requires-Dist: mypy (>=1.8) ; extra == "dev"
Requires-Dist: pydantic (>=2.0)
Requires-Dist: pytest (>=9.0.2) ; extra == "dev"
Requires-Dist: pytest-asyncio (>=1.3.0) ; extra == "dev"
Requires-Dist: pytest-cov (>=7.0.0) ; extra == "dev"
Requires-Dist: pyyaml (>=6.0)
Requires-Dist: ruff (>=0.2) ; extra == "dev"
Requires-Dist: twine (>=6.2.0) ; extra == "dev"
Requires-Dist: types-PyYAML (>=6.0) ; extra == "dev"
Project-URL: Changelog, https://github.com/alexh-scrt/flowengine/blob/master/CHANGELOG.md
Project-URL: Documentation, https://flowengine.readthedocs.io
Project-URL: Homepage, https://github.com/alexh-scrt/flowengine
Project-URL: Repository, https://github.com/alexh-scrt/flowengine
